midiphone/__init__.py
midiphone/__main__.py
midiphone/_assets.py
midiphone/_metadata.py
midiphone/py.typed
midiphone/resources/.gitkeep
midiphone-0.1.0.dist-info/entry_points.txt
midiphone-0.1.0.dist-info/LICENSE
midiphone-0.1.0.dist-info/METADATA
midiphone-0.1.0.dist-info/WHEEL
midiphone-0.1.0.dist-info/RECORD
