Metadata-Version: 2.1
Name: midiphone
Version: 0.1.0
Summary: Reconstruct MIDI notes over a virtual device from a live audio stream
Home-page: https://github.com/regulad/midiphone
License: GPL-3.0
Author: Parker Wahle
Author-email: regulad@regulad.xyz
Requires-Python: >=3.11,<3.13
Classifier: Development Status :: 1 - Planning
Classifier: License :: OSI Approved :: GNU General Public License v3 (GPLv3)
Classifier: Programming Language :: Python :: 3
Classifier: Programming Language :: Python :: 3.11
Classifier: Programming Language :: Python :: 3.12
Requires-Dist: importlib-metadata (>=6.8.0,<7.0.0)
Requires-Dist: mido (>=1.3.2,<2.0.0)
Requires-Dist: numpy (>=2.0.0,<3.0.0)
Requires-Dist: pyaudio (>=0.2.14,<0.3.0)
Requires-Dist: pytemidi (>=0.0.5,<0.0.6)
Requires-Dist: rich (>=13.7.1,<14.0.0)
Requires-Dist: scipy (>=1.13.1,<2.0.0)
Requires-Dist: typer[all] (>=0.9.0,<0.10.0)
Requires-Dist: typing-extensions (>=4.7.1,<5.0.0)
Project-URL: Changelog, https://github.com/regulad/midiphone/releases
Project-URL: Documentation, https://midiphone.readthedocs.io
Project-URL: Repository, https://github.com/regulad/midiphone
